<?xml version="1.0" encoding="UTF-8" standalone="yes" ?>
<!DOCTYPE boost_serialization>
<boost_serialization signature="serialization::archive" version="9">
<Root class_id="0" tracking_level="0" version="0">
	<pR class_id="1" tracking_level="0" version="0">
		<x>200</x>
		<y>150</y>
		<z>150</z>
	</pR>
	<v_redPointCenters class_id="2" tracking_level="0" version="0">
		<count>60</count>
		<item_version>0</item_version>
		<item>
			<x>0.053899077494020217</x>
			<y>0.002164154543297412</y>
			<z>0.67402788764890564</z>
		</item>
		<item>
			<x>0.053745960300058473</x>
			<y>0.0020813269792466435</y>
			<z>0.67409176959062067</z>
		</item>
		<item>
			<x>0.053745960300058473</x>
			<y>0.0020813269792466435</y>
			<z>0.67409176959062067</z>
		</item>
		<item>
			<x>0.053681186480860572</x>
			<y>0.0021098728099698642</y>
			<z>0.67367050600425538</z>
		</item>
		<item>
			<x>0.053694136419868213</x>
			<y>0.0021262676189655258</y>
			<z>0.67369905199771429</z>
		</item>
		<item>
			<x>0.053694136419868213</x>
			<y>0.0021262676189655258</y>
			<z>0.67369905199771429</z>
		</item>
		<item>
			<x>0.053726301934130805</x>
			<y>0.0020661456865149717</y>
			<z>0.67411119671863373</z>
		</item>
		<item>
			<x>0.053740438099540364</x>
			<y>0.0021211411087116369</y>
			<z>0.67390236083287547</z>
		</item>
		<item>
			<x>0.053965043415743166</x>
			<y>0.0018811998392557275</y>
			<z>0.67404250211002459</z>
		</item>
		<item>
			<x>0.053759863393922858</x>
			<y>0.0020332874005465108</y>
			<z>0.67411672837013514</z>
		</item>
		<item>
			<x>0.053757390299718107</x>
			<y>0.0020595965021467794</y>
			<z>0.67419555762851791</z>
		</item>
		<item>
			<x>0.053656448393460586</x>
			<y>0.0020739175754210144</y>
			<z>0.67344432861283354</z>
		</item>
		<item>
			<x>0.053554564162753657</x>
			<y>0.0022675406103143773</y>
			<z>0.67351594963337647</z>
		</item>
		<item>
			<x>0.053604773852801005</x>
			<y>0.002209975697764828</y>
			<z>0.67344078957968601</z>
		</item>
		<item>
			<x>0.053604773852801005</x>
			<y>0.002209975697764828</y>
			<z>0.67344078957968601</z>
		</item>
		<item>
			<x>0.053645359808610488</x>
			<y>0.0022007698612821272</y>
			<z>0.67337349379619993</z>
		</item>
		<item>
			<x>0.053733722693824468</x>
			<y>0.0021824621587860395</y>
			<z>0.67354120812141605</z>
		</item>
		<item>
			<x>0.053754812580317113</x>
			<y>0.0021197852331435209</y>
			<z>0.67415108232381027</z>
		</item>
		<item>
			<x>0.053668694736580605</x>
			<y>0.0021345172173076153</y>
			<z>0.67355201686576083</z>
		</item>
		<item>
			<x>0.053772582114948231</x>
			<y>0.001917713588497634</y>
			<z>0.67386015140931077</z>
		</item>
		<item>
			<x>0.053695026364812715</x>
			<y>0.0020060310264678298</y>
			<z>0.67382155048295522</z>
		</item>
		<item>
			<x>0.053670776364461825</x>
			<y>0.0019525293907228201</y>
			<z>0.67345645619190442</z>
		</item>
		<item>
			<x>0.053766289496355812</x>
			<y>0.0021821925868804569</y>
			<z>0.67390685484170132</z>
		</item>
		<item>
			<x>0.05375216524586944</x>
			<y>0.002186355749615683</y>
			<z>0.67377599380957709</z>
		</item>
		<item>
			<x>0.053699569439802974</x>
			<y>0.0021777532408121039</y>
			<z>0.67335530407225164</z>
		</item>
		<item>
			<x>0.053653038012566025</x>
			<y>0.0021360493401791809</y>
			<z>0.6733515581255668</z>
		</item>
		<item>
			<x>0.053637353404951321</x>
			<y>0.0021535515568539207</y>
			<z>0.67320015371148045</z>
		</item>
		<item>
			<x>0.053613896701638561</x>
			<y>0.0021378160220488981</y>
			<z>0.67324547547248947</z>
		</item>
		<item>
			<x>0.053677131839973601</x>
			<y>0.0021204436507462621</y>
			<z>0.67349090420051605</z>
		</item>
		<item>
			<x>0.053670842185691223</x>
			<y>0.0021371418063693415</y>
			<z>0.67357195621658905</z>
		</item>
		<item>
			<x>0.053644471304700812</x>
			<y>0.0021024438549188118</y>
			<z>0.67356618158128923</z>
		</item>
		<item>
			<x>0.053635567575652007</x>
			<y>0.0020980163708432947</y>
			<z>0.67359130723112126</z>
		</item>
		<item>
			<x>0.053619855193164701</x>
			<y>0.0021218378072688816</y>
			<z>0.67325789412007453</z>
		</item>
		<item>
			<x>0.053654251424068725</x>
			<y>0.0020318796186742684</y>
			<z>0.67344799437599534</z>
		</item>
		<item>
			<x>0.053619539769826821</x>
			<y>0.0020869451675727263</y>
			<z>0.67330370580995413</z>
		</item>
		<item>
			<x>0.053687987302719294</x>
			<y>0.0020909400387517096</y>
			<z>0.67357690560269634</z>
		</item>
		<item>
			<x>0.053688454964192681</x>
			<y>0.0019536981106100006</y>
			<z>0.67343468218956881</z>
		</item>
		<item>
			<x>0.053654902228681814</x>
			<y>0.0021575112881050719</y>
			<z>0.67352896268803286</z>
		</item>
		<item>
			<x>0.053810132110472628</x>
			<y>0.0020726906053791551</y>
			<z>0.67365103606926824</z>
		</item>
		<item>
			<x>0.053722040861156527</x>
			<y>0.0020371486988623698</y>
			<z>0.67397646453243987</z>
		</item>
		<item>
			<x>0.053631675135962037</x>
			<y>0.0021315718779239545</y>
			<z>0.67351265961279816</z>
		</item>
		<item>
			<x>0.05369690347861094</x>
			<y>0.0021084719689439257</y>
			<z>0.67351171466058002</z>
		</item>
		<item>
			<x>0.053673415437868972</x>
			<y>0.0020743395254782179</y>
			<z>0.67348904629891226</z>
		</item>
		<item>
			<x>0.053707520587612363</x>
			<y>0.0020779399478795327</y>
			<z>0.67400375370498455</z>
		</item>
		<item>
			<x>0.053678298795576181</x>
			<y>0.0020480194217977546</y>
			<z>0.67397324303907613</z>
		</item>
		<item>
			<x>0.053679945965509512</x>
			<y>0.002073192752843022</y>
			<z>0.67393578820253486</z>
		</item>
		<item>
			<x>0.05374641794618816</x>
			<y>0.002025277658548718</y>
			<z>0.67440301270777647</z>
		</item>
		<item>
			<x>0.053769854403024862</x>
			<y>0.0021144357543137343</y>
			<z>0.67402810572049332</z>
		</item>
		<item>
			<x>0.053708336589666887</x>
			<y>0.0021517636728731575</y>
			<z>0.67377733059523015</z>
		</item>
		<item>
			<x>0.053699976984921696</x>
			<y>0.0021179629535004046</y>
			<z>0.67415813006180048</z>
		</item>
		<item>
			<x>0.053692285346745888</x>
			<y>0.002145447745129158</y>
			<z>0.6741473198532586</z>
		</item>
		<item>
			<x>0.053710744182789809</x>
			<y>0.0021205586858511725</y>
			<z>0.6742903355582609</z>
		</item>
		<item>
			<x>0.053786251854527414</x>
			<y>0.0022157907441299474</y>
			<z>0.67392298950814511</z>
		</item>
		<item>
			<x>0.053880443599434169</x>
			<y>0.0022672511299112845</y>
			<z>0.67382599471753313</z>
		</item>
		<item>
			<x>0.053660205695411814</x>
			<y>0.0021973994652265301</y>
			<z>0.67381329174532922</z>
		</item>
		<item>
			<x>0.053567900350671396</x>
			<y>0.0021938465670053309</y>
			<z>0.67369585068157589</z>
		</item>
		<item>
			<x>0.053700246416708265</x>
			<y>0.0020856006460372341</y>
			<z>0.67405922409331354</z>
		</item>
		<item>
			<x>0.053684704207399889</x>
			<y>0.002136255806158522</y>
			<z>0.6735342829768769</z>
		</item>
		<item>
			<x>0.053715884939428138</x>
			<y>0.0020175669701281915</y>
			<z>0.67428858900883792</z>
		</item>
		<item>
			<x>0.053628878964699367</x>
			<y>0.002081333702904465</y>
			<z>0.67367454956574735</z>
		</item>
	</v_redPointCenters>
	<pM>
		<x>0.053699973490456743</x>
		<y>0.0021082374609236046</y>
		<z>0.67374207910084383</z>
	</pM>
	<pD>
		<x>283</x>
		<y>196</y>
		<z>162</z>
	</pD>
</Root>
</boost_serialization>

